fidat/ADL.py
fidat/ADX.py
fidat/ALMA.py
fidat/AO.py
fidat/APZ.py
fidat/ARO.py
fidat/ARSI.py
fidat/ASI.py
fidat/ATR.py
fidat/BASP.py
fidat/BASPN.py
fidat/BB.py
fidat/BBWIDTH.py
fidat/BC.py
fidat/BEARP.py
fidat/BOP.py
fidat/BPBP.py
fidat/BULLP.py
fidat/CCI.py
fidat/CFI.py
fidat/CHAIKIN.py
fidat/CHANDELIER.py
fidat/CMO.py
fidat/COPP.py
fidat/DC.py
fidat/DEI.py
fidat/DEMA.py
fidat/DI.py
fidat/DMI.py
fidat/DMMI.py
fidat/DPO.py
fidat/EFI.py
fidat/EFT.py
fidat/EIS.py
fidat/EMA.py
fidat/EMV.py
fidat/ERI.py
fidat/EVSTC.py
fidat/EVWMA.py
fidat/EVW_MACD.py
fidat/FISH.py
fidat/FRAMA.py
fidat/FVE.py
fidat/GHA.py
fidat/GMMA.py
fidat/HA.py
fidat/HLI.py
fidat/HMA.py
fidat/HMAO.py
fidat/HPO.py
fidat/ICHIMOKU.py
fidat/IFT_RSI.py
fidat/JMA.py
fidat/KAMA.py
fidat/KC.py
fidat/KEI.py
fidat/KST.py
fidat/LWMA.py
fidat/MACD.py
fidat/MAFI.py
fidat/MAMA.py
fidat/MFI.py
fidat/MI.py
fidat/MOBO.py
fidat/MOM.py
fidat/MSD.py
fidat/NVI.py
fidat/OBV.py
fidat/PAI.py
fidat/PERCENT_B.py
fidat/PIVOT.py
fidat/PIVOT_FIB.py
fidat/PPO.py
fidat/PRSK.py
fidat/PSAR.py
fidat/PSK.py
fidat/PVI.py
fidat/PZO.py
fidat/QSTICK.py
fidat/RMA.py
fidat/ROC.py
fidat/RSI.py
fidat/SAR.py
fidat/SDC.py
fidat/SMA.py
fidat/SMI.py
fidat/SMM.py
fidat/SMMA.py
fidat/SMO.py
fidat/SSMA.py
fidat/STC.py
fidat/STOCH.py
fidat/STOCHD.py
fidat/STOCHRSI.py
fidat/TEMA.py
fidat/TMF.py
fidat/TP.py
fidat/TR.py
fidat/TRIMA.py
fidat/TSI.py
fidat/UO.py
fidat/VAMA.py
fidat/VBM.py
fidat/VC.py
fidat/VFI.py
fidat/VIDYA.py
fidat/VO.py
fidat/VORTEX.py
fidat/VP.py
fidat/VPT.py
fidat/VWAP.py
fidat/VW_MACD.py
fidat/VZO.py
fidat/WF.py
fidat/WILLIAMS.py
fidat/WMA.py
fidat/WOBV.py
fidat/WP.py
fidat/WTO.py
fidat/ZCO.py
fidat/ZLEMA.py
fidat/__init__.py
fidat/__main__.py
fidat/Barriers/__init__.py
fidat/Cycle/__init__.py
fidat/Index/__init__.py
fidat/Momentum/__init__.py
fidat/Sentiment/__init__.py
fidat/Trends/__init__.py
fidat/Volatility/__init__.py
fidat/Volume/__init__.py
fidat-0.1.0.dist-info/METADATA
fidat-0.1.0.dist-info/WHEEL
fidat-0.1.0.dist-info/top_level.txt
fidat-0.1.0.dist-info/RECORD
