Metadata-Version: 2.1
Name: fidat
Version: 0.1.0
Summary: Framework for Intelligent Data Analysis and Trends
Author: Andy Hawkins
Author-email: projects@hawkins.tech
Maintainer: Hawkins.Tech Inc
Maintainer-email: projects@hawkins.tech
Keywords: data analysis,trend analysis,data assimilation,data visualization,statistical analysis,time series,predictive modeling,machine learning,data mining,big data,forecasting,pattern recognition,business intelligence,data science,quantitative analysis,financial analysis,market analysis,economic forecasting,data aggregation,data trends
Classifier: Development Status :: 4 - Beta
Classifier: Intended Audience :: Developers
Classifier: Topic :: Software Development :: Libraries
Classifier: Programming Language :: Python :: 3
Classifier: Programming Language :: Python :: 3.7
Classifier: Programming Language :: Python :: 3.8
Classifier: Programming Language :: Python :: 3.9
Classifier: Programming Language :: Python :: 3.10
Classifier: Programming Language :: Python :: 3.11
Classifier: Programming Language :: Python :: 3.12
Requires-Dist: pandas
Requires-Dist: numpy
Requires-Dist: pytest
Requires-Dist: pytest-cov
